setup.py
dansplotcore/__init__.py
dansplotcore/media.py
dansplotcore/plot.py
dansplotcore/primitives.py
dansplotcore/process.py
dansplotcore/show.py
dansplotcore/threed.py
dansplotcore/transforms.py
dansplotcore/vector_text.py
dansplotcore/voxel.py
dansplotcore.egg-info/PKG-INFO
dansplotcore.egg-info/SOURCES.txt
dansplotcore.egg-info/dependency_links.txt
dansplotcore.egg-info/requires.txt
dansplotcore.egg-info/top_level.txt